jedi_toolz/__init__.py
jedi_toolz/config.py
jedi_toolz/data.py
jedi_toolz/domo.py
jedi_toolz/functional.py
jedi_toolz/show.py
jedi_toolz/str_funcs.py
jedi_toolz/xlsx.py
jedi_toolz-0.0.21.dist-info/WHEEL
jedi_toolz-0.0.21.dist-info/METADATA
jedi_toolz-0.0.21.dist-info/RECORD
